django_rainbowtests-0.7.0.dist-info/licenses/AUTHORS.md
django_rainbowtests-0.7.0.dist-info/licenses/LICENSE.md
rainbowtests/__init__.py
rainbowtests/colors.py
rainbowtests/messages.py
rainbowtests/models.py
rainbowtests/tests.py
rainbowtests/views.py
rainbowtests/test/__init__.py
rainbowtests/test/core.py
rainbowtests/test/runner.py
rainbowtests/test/simple.py
django_rainbowtests-0.7.0.dist-info/METADATA
django_rainbowtests-0.7.0.dist-info/WHEEL
django_rainbowtests-0.7.0.dist-info/top_level.txt
django_rainbowtests-0.7.0.dist-info/RECORD
