Metadata-Version: 2.4
Name: django-rainbowtests
Version: 0.7.0
Summary: A colorful Django Test Runner.
Author-email: Brad Montgomery <brad@bradmontgomery.net>
License-Expression: MIT
Project-URL: Homepage, https://github.com/bradmontgomery/django-rainbowtests
Project-URL: Repository, https://github.com/bradmontgomery/django-rainbowtests
Classifier: Development Status :: 4 - Beta
Classifier: Environment :: Web Environment
Classifier: Framework :: Django
Classifier: Framework :: Django :: 4.2
Classifier: Framework :: Django :: 5.2
Classifier: Intended Audience :: Developers
Classifier: Operating System :: OS Independent
Classifier: Programming Language :: Python
Classifier: Programming Language :: Python :: 3
Classifier: Programming Language :: Python :: 3.10
Classifier: Programming Language :: Python :: 3.11
Classifier: Programming Language :: Python :: 3.12
Classifier: Programming Language :: Python :: 3.13
Classifier: Programming Language :: Python :: 3.14
Classifier: Topic :: Internet :: WWW/HTTP
Classifier: Topic :: Software Development :: Testing
Classifier: Topic :: Software Development :: Libraries :: Python Modules
Requires-Python: <3.15,>=3.10
License-File: LICENSE.md
License-File: AUTHORS.md
Requires-Dist: django<5.3,>=4.2
Requires-Dist: rich
Dynamic: license-file
